mapdeduce/__init__.py
mapdeduce/blup.py
mapdeduce/data.py
mapdeduce/dataframes.py
mapdeduce/helper.py
mapdeduce/hwas.py
mapdeduce/lmm.py
mapdeduce/mapseq.py
mapdeduce/munging.py
mapdeduce/permp.py
mapdeduce/plotting.py
mapdeduce/season.py
mapdeduce/scripts/__init__.py
mapdeduce/scripts/association_test.py
mapdeduce-2.2.2.dist-info/licenses/LICENSE
mapdeduce-2.2.2.dist-info/METADATA
mapdeduce-2.2.2.dist-info/WHEEL
mapdeduce-2.2.2.dist-info/entry_points.txt
mapdeduce-2.2.2.dist-info/top_level.txt
mapdeduce-2.2.2.dist-info/RECORD
