Metadata-Version: 2.4
Name: mapdeduce
Version: 2.2.2
Summary: Handling antigenic maps and sequence data, testing amino acid polymorphisms associated with antigenicity.
Author-email: David Pattinson <david.pattinson@wisc.edu>
License: Copyright 2023 David Joseph Pattinson
Project-URL: Homepage, https://github.com/acorg/mapdeduce
Keywords: influenza,lmm,antigenic cartography
Classifier: License :: OSI Approved :: MIT License
Classifier: Programming Language :: Python
Classifier: Programming Language :: Python :: 3
License-File: LICENSE
Requires-Dist: biopython
Requires-Dist: glimix-core
Requires-Dist: matplotlib
Requires-Dist: pandas
Requires-Dist: rpy2>=3.0.0
Requires-Dist: scikit-learn
Requires-Dist: scipy
Requires-Dist: seaborn
Requires-Dist: spm1d
Requires-Dist: tqdm
Provides-Extra: dev
Requires-Dist: black; extra == "dev"
Requires-Dist: pytest; extra == "dev"
Requires-Dist: flake8; extra == "dev"
Dynamic: license-file
